AUTHORS.rst
CHANGELOG.rst
INSTALL.rst
LICENSE.rst
MANIFEST.in
README.rst
VERSION
dev-requirements.txt
setup.py
psykorebase/__init__.py
psykorebase/cli.py
psykorebase.egg-info/PKG-INFO
psykorebase.egg-info/SOURCES.txt
psykorebase.egg-info/dependency_links.txt
psykorebase.egg-info/entry_points.txt
psykorebase.egg-info/not-zip-safe
psykorebase.egg-info/requires.txt
psykorebase.egg-info/top_level.txt
psykorebase/tests/__init__.py
psykorebase/tests/git.py