Metadata-Version: 1.1
Name: psykorebase
Version: 1.0.1
Summary: Easily perform safe (merge-based) rebases.
Home-page: https://github.com/benoitbryon/psykorebase
Author: Benoît Bryon
Author-email: benoit@marmelune.net
License: BSD
Keywords: git merge rebase
Platform: UNKNOWN
Classifier: Development Status :: 1 - Planning
Classifier: License :: OSI Approved :: BSD License
Classifier: Programming Language :: Python :: 2.7
Classifier: Programming Language :: Python :: 3.4
